tailscale_localapi/__init__.py
tailscale_localapi/_util/error.py
tailscale_localapi/_util/sock.py
tailscale_localapi/api.py
tailscale_localapi/v0/__init__.py
tailscale_localapi/v0/api.py
tailscale_localapi/v0/config.py
tailscale_localapi/v0/peers.py
tailscale_localapi-0.5.0.dist-info/LICENSE
tailscale_localapi-0.5.0.dist-info/METADATA
tailscale_localapi-0.5.0.dist-info/WHEEL
tailscale_localapi-0.5.0.dist-info/entry_points.txt
tailscale_localapi-0.5.0.dist-info/RECORD
