Metadata-Version: 2.1
Name: tailscale_localapi
Version: 0.5.0
Summary: Control Tailscale's local socket API
License: MIT
Author: Antoine POPINEAU
Author-email: antoine@popineau.eu
Requires-Python: >=3.10,<4.0
Classifier: License :: OSI Approved :: MIT License
Classifier: Programming Language :: Python :: 3
Classifier: Programming Language :: Python :: 3.10
Classifier: Programming Language :: Python :: 3.11
Classifier: Programming Language :: Python :: 3.12
Requires-Dist: requests (==2.29.0)
Requires-Dist: urllib3 (==1.26.16)
